[
  {
    "id": 1,
    "title": "Rainbow Unicorn Plush Toy",
    "description": "A soft and cuddly unicorn toy with rainbow mane and tail. Perfect for hugging and playing.",
    "price": 19.99,
    "discount_price": 14.99,
    "images": [
      "https://image.freepik.com/free-vector/cute-unicorn-plush-toy_24877-64338.jpg",
      "https://image.freepik.com/free-vector/cute-unicorn-plush-toy-with-rainbow-mane_24877-64339.jpg",
      "https://image.freepik.com/free-vector/cute-unicorn-plush-toy-with-heart_24877-64340.jpg",
      "https://image.freepik.com/free-vector/cute-unicorn-plush-toy-with-star_24877-64341.jpg"
    ],
    "quantity": 10,
    "categories": ["Toys", "Plush", "Unicorn"],
    "hot": false,
    "sale": true,
    "reviews": [
      {
        "name": "Alice",
        "rating": 5,
        "comment": "My daughter loves this unicorn! It's so soft and colorful."
      },
      {
        "name": "Bob",
        "rating": 4,
        "comment": "Nice toy, but a bit smaller than expected."
      }
    ]
  },
  {
    "id": 2,
    "title": "Kids Puzzle Set",
    "description": "A set of four puzzles with different themes: animals, vehicles, fruits and shapes. Each puzzle has 16 pieces and is made of durable cardboard.",
    "price": 12.99,
    "discount_price": null,
    "images": [
      "https://image.freepik.com/free-vector/kids-puzzle-set_52683-47201.jpg",
      "https://image.freepik.com/free-vector/kids-puzzle-set-with-animals_52683-47202.jpg",
      "https://image.freepik.com/free-vector/kids-puzzle-set-with-vehicles_52683-47203.jpg",
      "https://image.freepik.com/free-vector/kids-puzzle-set-with-fruits_52683-47204.jpg"
    ],
    "quantity": 20,
    "categories": ["Toys", "Puzzle", "Educational"],
    "hot": true,
    "sale": false,
    "reviews": [
      {
        "name": "Charlie",
        "rating": 5,
        "comment": "Great puzzles for kids. They are easy to assemble and have nice pictures."
      },
      {
        "name": "Diana",
        "rating": 3,
        "comment": "The puzzles are OK, but some pieces are bent and don't fit well."
      }
    ]
  },
  {
    "id": 3,
    "title": "Kids Painting Kit",
    "description": "A kit that includes 12 colors of washable paint, 6 brushes, 2 palettes, and a sketchbook. Ideal for unleashing your kid's creativity.",
    "price": 15.99,
    "discount_price": null,
    "images": [
      "https://image.freepik.com/free-vector/kids-painting-kit_24877-64342.jpg",
      "https://image.freepik.com/free-vector/kids-painting-kit-with-colors_24877-64343.jpg",
      "https://image.freepik.com/free-vector/kids-painting-kit-with-brushes_24877-64344.jpg",
      "https://image.freepik.com/free-vector/kids-painting-kit-with-sketchbook_24877-64345.jpg"
    ],
    "quantity": 15,
    "categories": ["Toys", "Painting", "Art"],
    "hot": false,
    "sale": false,
    "reviews": [
      {
        "name": "Evan",
        "rating": 5,
        "comment": "My son loves this kit. He paints every day and the colors are bright and easy to clean."
      },
      {
        "name": "Fiona",
        "rating": 4,
        "comment": "Good quality kit, but the sketchbook is a bit small."
      }
    ]
  },
  {
    "id": 4,
    "title": "Kids Lego Set",
    "description": "A set of 300 Lego bricks in various colors and shapes. Great for building anything your kid can imagine.",
    "price": 24.99,
    "discount_price": 19.99,
    "images": [
      "https://image.freepik.com/free-vector/kids-lego-set_24877-64346.jpg",
      "https://image.freepik.com/free-vector/kids-lego-set-with-bricks_24877-64347.jpg",
      "https://image.freepik.com/free-vector/kids-lego-set-with-car_24877-64348.jpg",
      "https://image.freepik.com/free-vector/kids-lego-set-with-house_24877-64349.jpg"
    ],
    "quantity": 12,
    "categories": ["Toys", "Lego", "Building"],
    "hot": true,
    "sale": true,
    "reviews": [
      {
        "name": "George",
        "rating": 5,
        "comment": "My daughter loves this Lego set. She plays with it every day and makes different things."
      },
      {
        "name": "Hannah",
        "rating": 4,
        "comment": "Nice Lego set, but some pieces are missing."
      }
    ]
  },
  {
    "id": 5,
    "title": "Kids Bicycle",
    "description": "A sturdy and safe bicycle for kids aged 5 to 10. It has a steel frame, 16-inch wheels, front and rear brakes, and a basket.",
    "price": 99.99,
    "discount_price": null,
    "images": [
      "https://image.freepik.com/free-vector/kids-bicycle_24877-64350.jpg",
      "https://image.freepik.com/free-vector/kids-bicycle-with-basket_24877-64351.jpg",
      "https://image.freepik.com/free-vector/kids-bicycle-with-helmet_24877-64352.jpg",
      "https://image.freepik.com/free-vector/kids-bicycle-with-balloon_24877-64353.jpg"
    ],
    "quantity": 8,
    "categories": ["Toys", "Bicycle", "Sports"],
    "hot": false,
    "sale": false,
    "reviews": [
      {
        "name": "Isaac",
        "rating": 5,
        "comment": "My son loves this bicycle. It's easy to ride and looks cool."
      },
      {
        "name": "Jenny",
        "rating": 3,
        "comment": "The bicycle is OK, but the basket is broken."
      }
    ]
  },
  {
    "id": 6,
    "title": "Kids Storybook",
    "description": "A collection of 10 classic fairy tales for kids, such as Cinderella, Snow White, and The Little Mermaid. Illustrated with colorful pictures and easy to read text.",
    "price": 9.99,
    "discount_price": 7.99,
    "images": [
      "https://image.freepik.com/free-vector/kids-storybook_24877-64354.jpg",
      "https://image.freepik.com/free-vector/kids-storybook-with-cinderella_24877-64355.jpg",
      "https://image.freepik.com/free-vector/kids-storybook-with-snow-white_24877-64356.jpg",
      "https://image.freepik.com/free-vector/kids-storybook-with-the-little-mermaid_24877-64357.jpg"
    ],
    "quantity": 25,
    "categories": ["Toys", "Storybook", "Reading"],
    "hot": false,
    "sale": true,
    "reviews": [
      {
        "name": "Kevin",
        "rating": 5,
        "comment": "My daughter loves this storybook. She reads it every night before bed."
      },
      {
        "name": "Laura",
        "rating": 4,
        "comment": "Nice storybook, but some pages are torn."
      }
    ]
  },
  {
    "id": 7,
    "title": "Kids Keyboard",
    "description": "A musical keyboard for kids with 37 keys, 8 tones, 8 rhythms, and 6 demo songs. It also has a microphone, a speaker, and a record function.",
    "price": 29.99,
    "discount_price": null,
    "images": [
      "https://image.freepik.com/free-vector/kids-keyboard_24877-64358.jpg",
      "https://image.freepik.com/free-vector/kids-keyboard-with-microphone_24877-64359.jpg",
      "https://image.freepik.com/free-vector/kids-keyboard-with-speaker_24877-64360.jpg",
      "https://image.freepik.com/free-vector/kids-keyboard-with-record-button_24877-64361.jpg"
    ],
    "quantity": 10,
    "categories": ["Toys", "Keyboard", "Music"],
    "hot": false,
    "sale": false,
    "reviews": [
      {
        "name": "Mark",
        "rating": 5,
        "comment": "My son loves this keyboard. He plays with it every day and sings along with the microphone."
      },
      {
        "name": "Nora",
        "rating": 3,
        "comment": "The keyboard is OK, but the speaker is too loud."
      }
    ]
  },
  {
    "id": 8,
    "title": "Kids Costume Set",
    "description": "A set of four costumes for kids to dress up as their favorite characters: a pirate, a princess, a superhero, and a dinosaur. Each costume includes a hat, a mask, and an outfit.",
    "price": 39.99,
    "discount_price": 34.99,
    "images": [
      "https://image.freepik.com/free-vector/kids-costume-set_24877-64362.jpg",
      "https://image.freepik.com/free-vector/kids-costume-set-with-pirate_24877-64363.jpg",
      "https://image.freepik.com/free-vector/kids-costume-set-with-princess_24877-64364.jpg",
      "https://image.freepik.com/free-vector/kids-costume-set-with-superhero_24877-64365.jpg"
    ],
    "quantity": 5,
    "categories": ["Toys", "Costume", "Role Play"],
    "hot": true,
    "sale": true,
    "reviews": [
      {
        "name": "Olivia",
        "rating": 5,
        "comment": "My kids love this costume set. They play with it every day and pretend to be different characters."
      },
      {
        "name": "Peter",
        "rating": 4,
        "comment": "Nice costume set, but the dinosaur mask is too big."
      }
    ]
  },
  {
    "id": 9,
    "title": "Kids Science Kit",
    "description": "A kit that includes 12 fun and educational science experiments for kids, such as making slime, growing crystals, and erupting a volcano. It comes with a manual, a safety goggles, and all the necessary materials.",
    "price": 49.99,
    "discount_price": null,
    "images": [
      "https://image.freepik.com/free-vector/kids-science-kit_24877-64366.jpg",
      "https://image.freepik.com/free-vector/kids-science-kit-with-slime_24877-64367.jpg",
      "https://image.freepik.com/free-vector/kids-science-kit-with-crystals_24877-64368.jpg",
      "https://image.freepik.com/free-vector/kids-science-kit-with-volcano_24877-64369.jpg"
    ],
    "quantity": 6,
    "categories": ["Toys", "Science", "Educational"],
    "hot": false,
    "sale": false,
    "reviews": [
      {
        "name": "Rachel",
        "rating": 5,
        "comment": "My kids love this science kit. They learn a lot and have fun at the same time."
      },
      {
        "name": "Sam",
        "rating": 3,
        "comment": "The science kit is OK, but some materials are missing."
      }
    ]
  },
  {
    "id": 10,
    "title": "Kids Dollhouse",
    "description": "A wooden dollhouse with four rooms, a balcony, and a staircase. It comes with 6 dolls, furniture, and accessories. It can be opened and closed for easy storage.",
    "price": 59.99,
    "discount_price": 49.99,
    "images": [
      "https://image.freepik.com/free-vector/kids-dollhouse_24877-64370.jpg",
      "https://image.freepik.com/free-vector/kids-dollhouse-with-dolls_24877-64371.jpg",
      "https://image.freepik.com/free-vector/kids-dollhouse-with-furniture_24877-64372.jpg",
      "https://image.freepik.com/free-vector/kids-dollhouse-with-accessories_24877-64373.jpg"
    ],
    "quantity": 4,
    "categories": ["Toys", "Dollhouse", "Role Play"],
    "hot": false,
    "sale": true,
    "reviews": [
      {
        "name": "Tina",
        "rating": 5,
        "comment": "My daughter loves this dollhouse. She plays with it every day and makes up stories."
      },
      {
        "name": "Victor",
        "rating": 4,
        "comment": "Nice dollhouse, but the staircase is loose."
      }
    ]
  }
]
